[
    [
        1262,
        [],
        "Turkey"
    ],
    "Answer the following questions:\nAnswer the following question based on the information in the given passage. Passage: Miletus (/ma\u026a\u02c8li\u02d0t\u0259s/; Ancient Greek: \u039c\u03af\u03bb\u03b7\u03c4\u03bf\u03c2, romanized:Mil\u0113tos; Hittite transcription Millawanda or Milawata (exonyms); Latin: Miletus; Turkish: Milet) was an ancient Greek city on the western coast of Anatolia, near the mouth of the Maeander River in ancient Caria.[3][4][5] Its ruins are located near the modern village of Balat in Ayd\u0131n Province, Turkey. Before the Persian invasion in the middle of the 6th century BC, Miletus was considered the greatest and wealthiest of Greek cities.[6][7] Question: Where is the Ionian city of Miletus located? Answer:",
    {
        "id": "english--3366301125197862232-0",
        "lang": "english",
        "summary": "Miletus (/ma\u026a\u02c8li\u02d0t\u0259s/; Ancient Greek: \u039c\u03af\u03bb\u03b7\u03c4\u03bf\u03c2, romanized:Mil\u0113tos; Hittite transcription Millawanda or Milawata (exonyms); Latin: Miletus; Turkish: Milet) was an ancient Greek city on the western coast of Anatolia, near the mouth of the Maeander River in ancient Caria.[3][4][5] Its ruins are located near the modern village of Balat in Ayd\u0131n Province, Turkey. Before the Persian invasion in the middle of the 6th century BC, Miletus was considered the greatest and wealthiest of Greek cities.[6][7]",
        "question": "Where is the Ionian city of Miletus located?",
        "label": "Turkey"
    }
]