[
    [
        2548,
        [],
        "a rapid and complete chlorosis, browning, then death of plant tissues such as leaves, branches, twigs, or floral organs"
    ],
    "Answer the following questions:\nAnswer the following question based on the information in the given passage. Passage: Blight is a rapid and complete chlorosis, browning, then death of plant tissues such as leaves, branches, twigs, or floral organs.[1]  Accordingly, many diseases that primarily exhibit this symptom are called blights. Several notable examples are: Question: What is blight in tomatoes? Answer:",
    {
        "id": "english--5222385841843339552-1",
        "lang": "english",
        "summary": "Blight is a rapid and complete chlorosis, browning, then death of plant tissues such as leaves, branches, twigs, or floral organs.[1]  Accordingly, many diseases that primarily exhibit this symptom are called blights. Several notable examples are:",
        "question": "What is blight in tomatoes?",
        "label": "a rapid and complete chlorosis, browning, then death of plant tissues such as leaves, branches, twigs, or floral organs"
    }
]