[
    [
        597,
        [],
        "80million"
    ],
    "Answer the following questions:\nAnswer the following question based on the information in the given passage. Passage: Of approximately 100 million native speakers of German in the world,[27] roughly 80million consider themselves Germans. There are an additional 80million people of German ancestry mainly in the United States, Brazil (mainly in the South Region of the country), Argentina, Canada, South Africa, the post-Soviet states (mainly in Russia and Kazakhstan), and France, each accounting for at least 1 million.[note 4] Thus, the total number of Germans lies somewhere between 100 and more than 150 million, depending on the criteria applied[1] (native speakers, single-ancestry ethnic Germans, partial German ancestry, etc.). Question: How many people are German? Answer:",
    {
        "id": "english-8779422158141987627-2",
        "lang": "english",
        "summary": "Of approximately 100 million native speakers of German in the world,[27] roughly 80million consider themselves Germans. There are an additional 80million people of German ancestry mainly in the United States, Brazil (mainly in the South Region of the country), Argentina, Canada, South Africa, the post-Soviet states (mainly in Russia and Kazakhstan), and France, each accounting for at least 1 million.[note 4] Thus, the total number of Germans lies somewhere between 100 and more than 150 million, depending on the criteria applied[1] (native speakers, single-ancestry ethnic Germans, partial German ancestry, etc.).",
        "question": "How many people are German?",
        "label": "80million"
    }
]