[
    [
        2828,
        [],
        "1903"
    ],
    "Answer the following questions:\nAnswer the following question based on the information in the given passage. Passage: The site on which the cathedral stands in the City of Westminster was purchased by the Diocese of Westminster in 1885, and construction was completed in 1903.[2] Westminster Cathedral is the largest Catholic church building in England and Wales and the seat of the Archbishop of Westminster. Question: When was Westminster Cathedral built? Answer:",
    {
        "id": "english-5564030102604355914-2",
        "lang": "english",
        "summary": "The site on which the cathedral stands in the City of Westminster was purchased by the Diocese of Westminster in 1885, and construction was completed in 1903.[2] Westminster Cathedral is the largest Catholic church building in England and Wales and the seat of the Archbishop of Westminster.",
        "question": "When was Westminster Cathedral built?",
        "label": "1903"
    }
]