[
    [
        2203,
        [],
        "northern region of Bosnia and Herzegovina"
    ],
    "Answer the following questions:\nAnswer the following question based on the information in the given passage. Passage: Bosnia (Serbo-Croatian: Bosna/\u0411\u043e\u0441\u043d\u0430; pronounced[b\u0254\u0302sna]) is the northern region of Bosnia and Herzegovina, encompassing roughly 81% of the country; the other eponymous region, the southern part, is Herzegovina. Bosnia is an informal term for the whole country. Question: Where is Bosnia? Answer:",
    {
        "id": "english--2872586940503514968-0",
        "lang": "english",
        "summary": "Bosnia (Serbo-Croatian: Bosna/\u0411\u043e\u0441\u043d\u0430; pronounced[b\u0254\u0302sna]) is the northern region of Bosnia and Herzegovina, encompassing roughly 81% of the country; the other eponymous region, the southern part, is Herzegovina. Bosnia is an informal term for the whole country.",
        "question": "Where is Bosnia?",
        "label": "northern region of Bosnia and Herzegovina"
    }
]