[
    [
        121,
        [],
        "1929"
    ],
    "Answer the following questions:\nAnswer the following question based on the information in the given passage. Passage: The Institutional Revolutionary Party  (Spanish: Partido Revolucionario Institucional, PRI) is a Mexican political party founded in 1929 that held uninterrupted power in the country for 71 years from 1929 to 2000, first as the National Revolutionary Party (Spanish: Partido Nacional Revolucionario, PNR), then as the Party of the Mexican Revolution (Spanish: Partido de la Revoluci\u00f3n Mexicana, PRM), and finally renaming itself as the Institutional Revolutionary Party in 1946. Question: When was the Institutional Revolutionary Party established in Mexico? Answer:",
    {
        "id": "english--5906788898094493615-0",
        "lang": "english",
        "summary": "The Institutional Revolutionary Party  (Spanish: Partido Revolucionario Institucional, PRI) is a Mexican political party founded in 1929 that held uninterrupted power in the country for 71 years from 1929 to 2000, first as the National Revolutionary Party (Spanish: Partido Nacional Revolucionario, PNR), then as the Party of the Mexican Revolution (Spanish: Partido de la Revoluci\u00f3n Mexicana, PRM), and finally renaming itself as the Institutional Revolutionary Party in 1946.",
        "question": "When was the Institutional Revolutionary Party established in Mexico?",
        "label": "1929"
    }
]