[
    [
        129,
        [],
        "Francis Gurry"
    ],
    "Answer the following questions:\nAnswer the following question based on the information in the given passage. Passage: WIPO currently has 191 member states,[6] administers 26 international treaties,[7] and is headquartered in Geneva, Switzerland. The current Director-General of WIPO is Francis Gurry, who took office on 1 October 2008.[8] 188 of the UN member states as well as the Cook Islands, Holy See and Niue are members of WIPO. Non-members are the states of Federated States of Micronesia, Nauru, Palau, Solomon Islands and South Sudan. Palestine has permanent observer status.[9] Question: Who is head of the World Intellectual Property Organization? Answer:",
    {
        "id": "english-3277035445278051433-1",
        "lang": "english",
        "summary": "WIPO currently has 191 member states,[6] administers 26 international treaties,[7] and is headquartered in Geneva, Switzerland. The current Director-General of WIPO is Francis Gurry, who took office on 1 October 2008.[8] 188 of the UN member states as well as the Cook Islands, Holy See and Niue are members of WIPO. Non-members are the states of Federated States of Micronesia, Nauru, Palau, Solomon Islands and South Sudan. Palestine has permanent observer status.[9]",
        "question": "Who is head of the World Intellectual Property Organization?",
        "label": "Francis Gurry"
    }
]