[
    [
        1409,
        [],
        "259"
    ],
    "Answer the following questions:\nAnswer the following question based on the information in the given passage. Passage: Judge began creating King of the Hill during his time making the MTV series Beavis and Butt-Head, which he also created and voiced. After pitching the pilot to Fox, Judge was paired with Greg Daniels, an experienced writer who previously worked on The Simpsons. The series debuted on the Fox network as a mid-season replacement in 1997, quickly becoming a hit. The series' popularity led to worldwide syndication, and reruns aired on Adult Swim from 2009 until 2018. As of July 24, 2018, reruns aired on Comedy Central. The show became one of Fox's longest-running series (third-longest as an animated series, behind The Simpsons and Family Guy).. A total of 259 episodes aired over the course of its 13 seasons. The final episode aired on Fox on September 13, 2009. Four episodes from the final season were to have aired on Fox, but later premiered in nightly syndication from May 3 to 6, 2010. Question: How many episodes did King of the Hill have? Answer:",
    {
        "id": "english-5828817002371994659-1",
        "lang": "english",
        "summary": "Judge began creating King of the Hill during his time making the MTV series Beavis and Butt-Head, which he also created and voiced. After pitching the pilot to Fox, Judge was paired with Greg Daniels, an experienced writer who previously worked on The Simpsons. The series debuted on the Fox network as a mid-season replacement in 1997, quickly becoming a hit. The series' popularity led to worldwide syndication, and reruns aired on Adult Swim from 2009 until 2018. As of July 24, 2018, reruns aired on Comedy Central. The show became one of Fox's longest-running series (third-longest as an animated series, behind The Simpsons and Family Guy).. A total of 259 episodes aired over the course of its 13 seasons. The final episode aired on Fox on September 13, 2009. Four episodes from the final season were to have aired on Fox, but later premiered in nightly syndication from May 3 to 6, 2010.",
        "question": "How many episodes did King of the Hill have?",
        "label": "259"
    }
]