[
    [
        2088,
        [],
        "1986"
    ],
    "Answer the following questions:\nAnswer the following question based on the information in the given passage. Passage: Zopiclone was developed and first introduced in 1986 by Rh\u00f4ne-Poulenc S.A., now part of Sanofi-Aventis, the main worldwide manufacturer. Initially, it was promoted as an improvement on benzodiazepines, but a recent meta-analysis found it was no better than benzodiazepines in any of the aspects assessed.[76] On April 4, 2005, the U.S. Drug Enforcement Administration listed zopiclone under schedule IV, due to evidence that the drug has addictive properties similar to benzodiazepines. Question: When was Zopiclone first introduced? Answer:",
    {
        "id": "english--7067640642667218462-25",
        "lang": "english",
        "summary": "Zopiclone was developed and first introduced in 1986 by Rh\u00f4ne-Poulenc S.A., now part of Sanofi-Aventis, the main worldwide manufacturer. Initially, it was promoted as an improvement on benzodiazepines, but a recent meta-analysis found it was no better than benzodiazepines in any of the aspects assessed.[76] On April 4, 2005, the U.S. Drug Enforcement Administration listed zopiclone under schedule IV, due to evidence that the drug has addictive properties similar to benzodiazepines.",
        "question": "When was Zopiclone first introduced?",
        "label": "1986"
    }
]